MANIFEST.in
README.rst
setup.py
saddle/__init__.py
saddle/cli.py
saddle/lint.py
saddle/runner.py
saddle/saddle_dir.py
saddle/saddle_fixture.py
saddle/saddle_service.py
saddle/saddle_service_logs.py
saddle/saddle_traceback.py
saddle/search.py
saddle/service_engine.py
saddle/tags.py
saddle/testcase.py
saddle.egg-info/PKG-INFO
saddle.egg-info/SOURCES.txt
saddle.egg-info/dependency_links.txt
saddle.egg-info/entry_points.txt
saddle.egg-info/not-zip-safe
saddle.egg-info/requires.txt
saddle.egg-info/top_level.txt
saddle/libfaketime/Makefile
saddle/libfaketime/Makefile.OSX
saddle/libfaketime/__init__.py
saddle/libfaketime/faketime
saddle/libfaketime/faketime.c
saddle/libfaketime/faketime_common.h
saddle/libfaketime/libfaketime.c
saddle/libfaketime/libfaketime.map
saddle/libfaketime/sunos_endian.h
saddle/libfaketime/time_ops.h
saddle/libfaketime/timeprivacy
saddle/services/__init__.py
saddle/services/celery_service.py
saddle/services/django_service.py
saddle/services/postgres_service.py
saddle/services/redis_service.py
saddle/services/saddlesmtp_service.py