Metadata-Version: 1.1
Name: saddle
Version: 0.1.1
Summary: Functional testing framework.
Home-page: https://saddle.readthedocs.org/
Author: Colm O'Connor
Author-email: colm.oconnor.github@gmail.com
License: GPLv3
Keywords: functional test harness framework process orchestration selenium
Platform: UNKNOWN
Classifier: Development Status :: 3 - Alpha
Classifier: Intended Audience :: Developers
Classifier: License :: OSI Approved :: GNU Library or Lesser General Public License (LGPL)
Classifier: Topic :: Software Development :: Quality Assurance
Classifier: Topic :: Software Development :: Testing
Classifier: Topic :: Software Development :: Libraries
Classifier: Programming Language :: Python :: 2
Classifier: Programming Language :: Python :: 2.6
Classifier: Programming Language :: Python :: 2.7
